odoo/addons/sale_order_line_menu/README.rst
odoo/addons/sale_order_line_menu/__init__.py
odoo/addons/sale_order_line_menu/__manifest__.py
odoo/addons/sale_order_line_menu/i18n/de.po
odoo/addons/sale_order_line_menu/i18n/es.po
odoo/addons/sale_order_line_menu/i18n/fr.po
odoo/addons/sale_order_line_menu/i18n/fr_BE.po
odoo/addons/sale_order_line_menu/i18n/fr_FR.po
odoo/addons/sale_order_line_menu/i18n/hr.po
odoo/addons/sale_order_line_menu/i18n/it.po
odoo/addons/sale_order_line_menu/i18n/pt_BR.po
odoo/addons/sale_order_line_menu/i18n/sale_order_line_menu.pot
odoo/addons/sale_order_line_menu/models/__init__.py
odoo/addons/sale_order_line_menu/models/sale_order_line.py
odoo/addons/sale_order_line_menu/readme/CONTRIBUTORS.md
odoo/addons/sale_order_line_menu/readme/DESCRIPTION.md
odoo/addons/sale_order_line_menu/readme/USAGE.md
odoo/addons/sale_order_line_menu/static/description/icon.png
odoo/addons/sale_order_line_menu/static/description/index.html
odoo/addons/sale_order_line_menu/views/sale_order_line_views.xml
odoo_addon_sale_order_line_menu-18.0.1.0.0.6.dist-info/METADATA
odoo_addon_sale_order_line_menu-18.0.1.0.0.6.dist-info/WHEEL
odoo_addon_sale_order_line_menu-18.0.1.0.0.6.dist-info/top_level.txt
odoo_addon_sale_order_line_menu-18.0.1.0.0.6.dist-info/RECORD
