Metadata-Version: 2.1
Name: odoo-addon-sale_order_line_menu
Version: 18.0.1.0.0.6
Requires-Python: >=3.10
Requires-Dist: odoo==18.0.*
Summary: Adds a Sale Order Lines Menu
Home-page: https://github.com/OCA/sale-workflow
License: AGPL-3
Author: Open Source Integrators, Odoo Community Association (OCA)
Author-email: support@odoo-community.org
Classifier: Programming Language :: Python
Classifier: Framework :: Odoo
Classifier: Framework :: Odoo :: 18.0
Classifier: License :: OSI Approved :: GNU Affero General Public License v3
Classifier: Development Status :: 4 - Beta
